MANIFEST.in
README.md
setup.cfg
setup.py
./LICENSE.txt
./README.md
./setup.py
./Miscellanea/ptemcee_run.py
./SRPSTATS/Akaike.py
./SRPSTATS/AsymmetricGaussianDistrib.py
./SRPSTATS/AverIterSigmaClipp.py
./SRPSTATS/AverSigmaClippFrame.py
./SRPSTATS/AverSigmaClippFrameFast.py
./SRPSTATS/BIC.py
./SRPSTATS/BayesFactor.py
./SRPSTATS/Bayespvalue.py
./SRPSTATS/ChiSqIncrement.py
./SRPSTATS/CoordDistanceMinimization.py
./SRPSTATS/FTest.py
./SRPSTATS/GenFitPars.py
./SRPSTATS/GenGaussSet.py
./SRPSTATS/LucyBayespvalue.py
./SRPSTATS/MAD.py
./SRPSTATS/Pandas_CCF.py
./SRPSTATS/RebinData.py
./SRPSTATS/SSE.py
./SRPSTATS/ScoreatPercentile.py
./SRPSTATS/SkyDistanceMinimization.py
./SRPSTATS/StDev.py
./SRPSTATS/WeightedMean.py
./SRPSTATS/WeightedMeanFrame.py
./SRPSTATS/XCorr_1D.py
./SRPSTATS/__init__.py
./SRPSTATS/chi2.py
./SRPSTATS/pvalue.py
./SRPSTATS/FT/ACF.py
./SRPSTATS/FT/FourierPeriodogram.py
./SRPSTATS/FT/__init__.py
./SRPSTATS/FT/fftransform.py
./SRPSTATS/GP/AEKernel.py
./SRPSTATS/GP/CosineKernel.py
./SRPSTATS/GP/ExpSineKernel.py
./SRPSTATS/GP/MaternKernel.py
./SRPSTATS/GP/PSDMatern.py
./SRPSTATS/GP/PSDSE.py
./SRPSTATS/GP/RQKernel.py
./SRPSTATS/GP/SEKernel.py
./SRPSTATS/GP/__init__.py
./SRPSTATS/MCMC/__init__.py
./SRPSTATS/MCMC/emcee_run.py
./SRPSTATS/MCMC/ptemcee_run.py
./SRPSTATS/MCMC/quartile.py
./build/lib/SRPSTATS/Akaike.py
./build/lib/SRPSTATS/AsymmetricGaussianDistrib.py
./build/lib/SRPSTATS/AverIterSigmaClipp.py
./build/lib/SRPSTATS/AverSigmaClippFrame.py
./build/lib/SRPSTATS/AverSigmaClippFrameFast.py
./build/lib/SRPSTATS/BIC.py
./build/lib/SRPSTATS/BayesFactor.py
./build/lib/SRPSTATS/Bayespvalue.py
./build/lib/SRPSTATS/ChiSqIncrement.py
./build/lib/SRPSTATS/CoordDistanceMinimization.py
./build/lib/SRPSTATS/FTest.py
./build/lib/SRPSTATS/GenFitPars.py
./build/lib/SRPSTATS/GenGaussSet.py
./build/lib/SRPSTATS/LucyBayespvalue.py
./build/lib/SRPSTATS/MAD.py
./build/lib/SRPSTATS/Pandas_CCF.py
./build/lib/SRPSTATS/RebinData.py
./build/lib/SRPSTATS/SSE.py
SRPAstro.STATS.egg-info/PKG-INFO
SRPAstro.STATS.egg-info/SOURCES.txt
SRPAstro.STATS.egg-info/dependency_links.txt
SRPAstro.STATS.egg-info/requires.txt
SRPAstro.STATS.egg-info/top_level.txt
